pixelartconv/__init__.py
pixelartconv/__main__.py
pixelartconv/file_management.py
pixelartconv/help.py
pixelartconv/logic.py
pixelartconv/script.py
pixelartconv-1.2.1.dist-info/METADATA
pixelartconv-1.2.1.dist-info/WHEEL
pixelartconv-1.2.1.dist-info/entry_points.txt
pixelartconv-1.2.1.dist-info/top_level.txt
pixelartconv-1.2.1.dist-info/RECORD
