Metadata-Version: 2.4
Name: pixelartconv
Version: 1.2.1
Summary: PixelArtConv - Pixel Art Converter
Author-email: Simon Ruzicka <simon.ruzicka@protonmail.com>
Project-URL: Homepage, https://github.com/ruzicka02/paconv
Classifier: Programming Language :: Python :: 3
Classifier: License :: OSI Approved :: MIT License
Classifier: Operating System :: OS Independent
Requires-Python: >=3.9
Requires-Dist: numpy<2,>=1.23
Requires-Dist: Pillow>=9
Requires-Dist: colorthief
Requires-Dist: opencv-python
